marlenv/__init__.py
marlenv/wrappers.py
marlenv/core/__init__.py
marlenv/core/grid_util.py
marlenv/core/snake.py
marlenv/envs/__init__.py
marlenv/envs/constants.py
marlenv/envs/coop_snake_env.py
marlenv/envs/graph_snake_env.py
marlenv/envs/snake_env.py
tests/__init__.py
tests/test_snake.py
marlenv-1.0.1.dist-info/METADATA
marlenv-1.0.1.dist-info/WHEEL
marlenv-1.0.1.dist-info/top_level.txt
marlenv-1.0.1.dist-info/RECORD
