Metadata-Version: 2.1
Name: marlenv
Version: 1.0.1
Home-page: https://github.com/kc-ml2/marlenv
Author: Tae Min Ha, Daniel Nam, Won Seok Jung
Author-email: contact@kc-ml2.com
Requires-Python: >=3.8
Requires-Dist: gym (==0.24.1)
